PageXML_to_Mask_converter-0.2.data/data/requirements.txt
pagexml_mask_converter/__init__.py
pagexml_mask_converter/color_legend.py
pagexml_mask_converter/data.py
pagexml_mask_converter/pagexml_to_mask.py
pagexml_mask_converter/test.py
PageXML_to_Mask_converter-0.2.dist-info/LICENSE.md
PageXML_to_Mask_converter-0.2.dist-info/METADATA
PageXML_to_Mask_converter-0.2.dist-info/WHEEL
PageXML_to_Mask_converter-0.2.dist-info/entry_points.txt
PageXML_to_Mask_converter-0.2.dist-info/top_level.txt
PageXML_to_Mask_converter-0.2.dist-info/RECORD
